baisstools/__init__.py
baisstools/path.py
baisstools/files/__init__.py
baisstools/github/__init__.py
baisstools/github/workflows.py
baisstools/gitrepo/__init__.py
baisstools/norms/__init__.py
baisstools-0.0.4.dist-info/licenses/LICENSE
baisstools-0.0.4.dist-info/METADATA
baisstools-0.0.4.dist-info/WHEEL
baisstools-0.0.4.dist-info/top_level.txt
baisstools-0.0.4.dist-info/RECORD
